typed_out/__init__.py
typed_out/__main__.py
typed_out/app.py
typed_out/main.py
typed_out-0.0.1.dist-info/METADATA
typed_out-0.0.1.dist-info/WHEEL
typed_out-0.0.1.dist-info/top_level.txt
typed_out-0.0.1.dist-info/RECORD
